mcp_server_zoom/__init__.py
mcp_server_zoom/__main__.py
mcp_server_zoom/server.py
mcp_server_zoom-0.1.0.dist-info/METADATA
mcp_server_zoom-0.1.0.dist-info/WHEEL
mcp_server_zoom-0.1.0.dist-info/entry_points.txt
mcp_server_zoom-0.1.0.dist-info/RECORD
